<?xml version="1.0" encoding="UTF-8"?>
<T3locallangExt>
  <data type="array">
    <languageKey index="ro" type="array">
			<label index="100">100</label>
			<label index="1000">1000</label>
			<label index="20">20</label>
			<label index="200">200</label>
			<label index="50">50</label>
			<label index="500">500</label>
			<label index="action">Acțiune:</label>
			<label index="action_1_1">Inserare</label>
			<label index="action_1_2">Actualizare</label>
			<label index="action_1_3">Ștergere</label>
			<label index="action_1_4">Mută</label>
			<label index="action_1_5">Verificare</label>
			<label index="action_2_1"/>
			<label index="action_2_2"/>
			<label index="action_2_3">Mută</label>
			<label index="action_2_4">Ștergere</label>
			<label index="action_2_5"/>
			<label index="action_254_1"/>
			<label index="action_255_1"/>
			<label index="action_255_2"/>
			<label index="action_255_3"/>
			<label index="action_2_6"/>
			<label index="action_2_7"/>
			<label index="action_2_8"/>
			<label index="action_2_9"/>
			<label index="action_3_1"/>
			<label index="actionAll">Toate</label>
			<label index="actionCache">Cache</label>
			<label index="actionDatabase">Baza de date</label>
			<label index="actionErrors">Erori</label>
			<label index="actionFile">Fișier</label>
			<label index="actionLogin">Login</label>
			<label index="actionSettings">Setări</label>
			<label index="adminLog">Administrare jurnal log</label>
			<label index="allUsers">[Toți utilizatorii]</label>
			<label index="any">[Oricare]</label>
			<label index="changesInFields">Modificări în cîmpurile: %s</label>
			<label index="chLog_l_action">Acțiune:</label>
			<label index="chLog_l_details"/>
			<label index="chLog_l_error"/>
			<label index="chLog_l_table"/>
			<label index="chLog_l_time">Oră:</label>
			<label index="chLog_l_types"/>
			<label index="chLog_l_user">Utilizator:</label>
			<label index="chLog_menuDepth"/>
			<label index="chLog_menuTime">Oră:</label>
			<label index="chLog_menuUsers">Utilizatori:</label>
			<label index="chLog_time_0">Această săptămînă</label>
			<label index="chLog_time_1">Săptămînă trecută</label>
			<label index="chLog_time_10">Luna curentă</label>
			<label index="chLog_time_11">Ultima lună</label>
			<label index="chLog_time_12">Ultimele 31 de zile</label>
			<label index="chLog_time_2">Ultimele 7 zile</label>
			<label index="chLog_time_20">Nici o limită</label>
			<label index="chLog_title"/>
			<label index="chLog_users_0">[Toți utilizatorii]</label>
			<label index="chLog_users_-1">Propriu</label>
			<label index="draft">Ciornă</label>
			<label index="forNonPageRelatedActions">pentru acțiuni NON-PAGE</label>
			<label index="forPage">pentru PAGE "%s" (UID: %s)</label>
			<label index="forRootLevel">pentru ROOT LEVEL</label>
			<label index="group">Grup:</label>
			<label index="groupByPage">Grupat după pagină:</label>
			<label index="last31Days">Ultimele 31 de zile</label>
			<label index="last7Days">Ultimele 7 zile</label>
			<label index="lastMonth">Ultima lună</label>
			<label index="lastWeek">Săptămînă trecută</label>
			<label index="live">LIVE</label>
			<label index="logForNonPageRelatedActionsOrRootLevelOrPage">Jurnal %s de la %s la %s</label>
			<label index="max">Max:</label>
			<label index="msg_1_0_1">Referer-ul gazdă '%s' și serverul gazdă '%s' nu se potrivesc!</label>
			<label index="msg_1_1_11">Încercare de a insera conținut pe pagina '%s' (%s) unde această tabelă, %s, nu este permisă</label>
			<label index="msg_1_1_12">Încercare de a insera conținut pe pagina '%s' (%s) din tabela '%s' fără autorizare. Sau pagina nu există.</label>
			<label index="msg_1_2_1">Încercare de modificare a tabelei '%s' fără autorizare</label>
			<label index="msg_1_2_10">Înregistrarea '%s' (%s) a fost actualizată.</label>
			<label index="msg_1_2_12">Eroare MySQL: '%s' (%s)</label>
			<label index="msg_1_2_2">Încercare de modificare a înregistrării '%s' (%s) fără autorizare. Sau pagina nu există.</label>
			<label index="msg_1_4_1">Încercare de a muta înregistrarea '%s' (%s) după o înregistrare ce nu există (uid=%s)</label>
			<label index="msg_1_4_10">Încercare de a muta pagina '%s' (%s) în interiorul propriei rădăcini (la pagina '%s' (%s))</label>
			<label index="msg_1_4_11">Încercare de a insera o înregistrare pe pagina '%s' (%s) unde această tabelă, %s, nu este permisă</label>
			<label index="msg_1_4_12">Încercare de a insera o înregistrare pe pagina '%s' (%s) din tabela '%s' fără autorizare. Sau pagina nu există.</label>
			<label index="msg_1_4_13"/>
			<label index="msg_1_4_14"/>
			<label index="msg_1_4_2">Înregistrarea '%s' (%s) a fost mutată la pagina '%s' (%s)</label>
			<label index="msg_1_4_3">Înregistrarea '%s' (%s) a fost mutată de pe pagina '%s' (%s)</label>
			<label index="msg_1_4_4">Înregistrarea '%s' (%s) a fost mutată pe pagina '%s' (%s)</label>
			<label index="msg_1_5_1"/>
			<label index="msg_1_5_10"/>
			<label index="msg_1_5_11"/>
			<label index="msg_1_5_12"/>
			<label index="msg_1_5_13"/>
			<label index="msg_1_5_14"/>
			<label index="msg_1_5_15"/>
			<label index="msg_1_5_16"/>
			<label index="msg_1_5_2"/>
			<label index="msg_1_5_3"/>
			<label index="msg_2_9_1"/>
			<label index="noLimit">Nici o limită</label>
			<label index="overview">Vedere de ansamblu</label>
			<label index="pagenameWithUID">%s" [UID: %s]</label>
			<label index="self">Propriu</label>
			<label index="set">Fixare</label>
			<label index="showHistory">Arată istoricul</label>
			<label index="thisMonth">Luna curentă</label>
			<label index="thisWeek">Această săptămînă</label>
			<label index="time">Oră:</label>
			<label index="timeInfo">Aceste pagini au mesaje de jurnal de la %s la %s</label>
			<label index="type_1">BDD</label>
			<label index="type_2"/>
			<label index="type_254"/>
			<label index="type_255"/>
			<label index="type_3"/>
			<label index="user">Utilizator:</label>
			<label index="userDefined">Definit de utilizator</label>
			<label index="userGroup">Grup:</label>
			<label index="users">Utilizatori:</label>
			<label index="workspace">Spațiu de lucru:</label>
		</languageKey>
  </data>
</T3locallangExt>
